intake_stripe/__init__.py
intake_stripe/_version.py
intake_stripe/core.py
tests/__init__.py
intake_stripe-0.0.4.dist-info/LICENSE
intake_stripe-0.0.4.dist-info/METADATA
intake_stripe-0.0.4.dist-info/WHEEL
intake_stripe-0.0.4.dist-info/entry_points.txt
intake_stripe-0.0.4.dist-info/top_level.txt
intake_stripe-0.0.4.dist-info/RECORD
