Metadata-Version: 2.1
Name: intake-stripe
Version: 0.0.4
Summary: Intake driver to load Stripe data
Home-page: https://github.com/sophiamyang/intake-stripe
Author: Sophia Yang
Author-email: UNKNOWN
License: BSD
Keywords: intake-stripe
Platform: UNKNOWN
Classifier: Programming Language :: Python :: 2.7
Classifier: Programming Language :: Python :: 3.6
Classifier: Programming Language :: Python :: 3.7
Requires-Dist: stripe
Requires-Dist: intake
Requires-Dist: pandas
